{
  "schema": "tinycloud.share-email-claim/release-evidence-v2",
  "generatedAt": "2026-07-20T04:52:36.745Z",
  "heads": {
    "share": "184f5a7423ffeef5fe04035efa63fbd730b1d03e",
    "node": "afed9261a67adb2c1ea0e6edad2ba3daeddfcd46",
    "opencredentials": "a7c075ca5ed9f7e2784586b7a8a896804ef3788d"
  },
  "contract": {
    "commit": "36f6c4303eca3bee917692c77237c264b4dfa342",
    "manifestDigest": "pl8-1Rpx_DYCBjOpK3hRrLfrSVDINNFssZDfFw6BMTs",
    "manifestFiles": {
      "positive.json": "LeUBRvznxoSqHsaSms_mGWoJiMN_LTRcgS0EpE35oWA",
      "negative.json": "HU6oz7nYywuR9_pdPGJHr_WGhClPNVz63_-ATfHs4oI",
      "states.json": "I5vwcw3UyGqnLUZFMONW3Mz4NB9fMYV4n8VxpjyeKDI",
      "build.mjs": "m4fYop89RBL9cHHj268A5z1B7DqIcu7B8yZ0NttfCjk",
      "validate.mjs": "bM9YFXiEWrTzXdLxUt33bf5_LiV40iF-QX86_fxD-9g",
      "loader.ts": "_N-1_IjNOXrm_4p6ObsyFjWvXHcFieixqqFntyWkVkg",
      "rust/Cargo.toml": "NMdpBiBPFtiy1N9yBltyPtR6UPUwV-WFTNf2s_dnnIU",
      "rust/Cargo.lock": "rWXLVvO1r531D1y3-SZjjqoknzpkOb6wjqTmhcFBZ-U",
      "rust/src/main.rs": "p5uAJFLsgCl_2oJelsCZmRqFDD-rjgwBXHEygmm7W1g",
      "domains.json": "HIIBpz9hDgnN28isDQv9nYcq20VnhETcS3Ph6D2_uvg",
      "schemas.json": "KfbG7RiXhkMr1C2q3BZhlaxDV4KWxhGMzoIMZ-tGyoc",
      "authority-material.schema.json": "EYIzrAtgNmICrvYABSOssEfYXhX778ula7y9htWZ1ys",
      "README.md": "sXnqXpmFo99s1xgyk95r1lN5v8Q7XdhW12qz7X5wgbk"
    }
  },
  "commands": {
    "vectorValidation": "node test/vectors/email-claim-v1/validate.mjs",
    "shareTest": "npm test",
    "shareTypecheck": "npm run typecheck",
    "shareBuild": "npm run build",
    "joinedBrowserRun1": "npm run test:e2e:email",
    "joinedBrowserRun2": "npm run test:e2e:email"
  },
  "runs": [
    {
      "runId": "round32-gate-1-repair",
      "start": "2026-07-20T04:46:50.081Z",
      "end": "2026-07-20T04:48:11.272Z",
      "durationMs": 81191,
      "exitStatus": 0,
      "command": "/Users/samgbafa/.nvm/versions/node/v20.19.4/bin/node /Users/samgbafa/conductor/workspaces/tinycloud-dev/shanghai/worktrees/share/feat/email-claim-e1-e2e/test/e2e-email/integration.mjs",
      "logDigest": "4321afa9a4333c0e6ebe2a3ba02c47ae8642f22d2edfa4b32a1ba72d4ce117c9",
      "artifactHash": "d923726a7c48072341648411ad0ec2f842577869c4a92f94c501f3e7ff60c16b",
      "toolVersions": {
        "node": "v20.19.4",
        "npm": "10.8.2",
        "git": "git version 2.50.1 (Apple Git-155)",
        "cargo": "cargo 1.97.0 (c980f4866 2026-06-30)",
        "chromium": "puppeteer-managed"
      },
      "coverage": {
        "fixtures": 4,
        "sources": [
          "kv",
          "sql"
        ],
        "browser": [
          "KV",
          "named-SQL",
          "scanner-safe inert GET",
          "explicit activation",
          "non-extractable holder key",
          "signed challenge/session/read verification",
          "post-claim resend suppression",
          "accessibility/mobile"
        ],
        "negativeBoundaryCases": [
          "authoritative binding propagation",
          "forged policy challenge",
          "misbound read response",
          "terminal claim states",
          "activation replay"
        ],
        "binding": "independent-provisioned"
      },
      "cleanup": {
        "stopped": 5,
        "remaining": [],
        "complete": true
      },
      "recordDigest": "46f3b0c390ac7e01110d25f69d0396ad3616aa21bfcc9faef1a4e9772f3681a2"
    },
    {
      "runId": "round32-gate-2-repair",
      "start": "2026-07-20T04:48:35.108Z",
      "end": "2026-07-20T04:49:45.093Z",
      "durationMs": 69985,
      "exitStatus": 0,
      "command": "/Users/samgbafa/.nvm/versions/node/v20.19.4/bin/node /Users/samgbafa/conductor/workspaces/tinycloud-dev/shanghai/worktrees/share/feat/email-claim-e1-e2e/test/e2e-email/integration.mjs",
      "logDigest": "75d352bcf4f55547398ff3678de0b9a81da5a43e48189c87489aa11bb4ae72a2",
      "artifactHash": "12d8e70a351e8f0569f22c04d568fa3fde1784efa3097a5e4b2aa39f1d7daa71",
      "toolVersions": {
        "node": "v20.19.4",
        "npm": "10.8.2",
        "git": "git version 2.50.1 (Apple Git-155)",
        "cargo": "cargo 1.97.0 (c980f4866 2026-06-30)",
        "chromium": "puppeteer-managed"
      },
      "coverage": {
        "fixtures": 4,
        "sources": [
          "kv",
          "sql"
        ],
        "browser": [
          "KV",
          "named-SQL",
          "scanner-safe inert GET",
          "explicit activation",
          "non-extractable holder key",
          "signed challenge/session/read verification",
          "post-claim resend suppression",
          "accessibility/mobile"
        ],
        "negativeBoundaryCases": [
          "authoritative binding propagation",
          "forged policy challenge",
          "misbound read response",
          "terminal claim states",
          "activation replay"
        ],
        "binding": "independent-provisioned"
      },
      "cleanup": {
        "stopped": 5,
        "remaining": [],
        "complete": true
      },
      "recordDigest": "dfb0a051e7509d979fa936e8b46d7c0a83ac496ebbb06d7e55d9b8183d6c7449"
    }
  ],
  "results": {
    "status": "passed",
    "cleanRuns": 2,
    "generatedBy": "release:evidence",
    "siweProvenance": {
      "status": "supplied",
      "toolchain": {
        "node": "v20.19.4",
        "npm": "10.8.2",
        "git": "git version 2.50.1 (Apple Git-155)",
        "cargo": "cargo 1.97.0 (c980f4866 2026-06-30)",
        "chromium": "puppeteer-managed"
      },
      "originMainHead": "a78e94d893c805869911b31900597ffadb29bc5b",
      "featureHead": "afed9261a67adb2c1ea0e6edad2ba3daeddfcd46",
      "command": "cargo 1.97.0 (c980f4866 2026-06-30); see .context/email-claim-siwe-round32-provenance.json; origin/main and feature-head both exit 101 with 8/9 tests passed and verification1 failure"
    }
  },
  "toolVersions": {
    "node": "v20.19.4",
    "npm": "10.8.2",
    "git": "git version 2.50.1 (Apple Git-155)",
    "cargo": "cargo 1.97.0 (c980f4866 2026-06-30)",
    "chromium": "puppeteer-managed"
  },
  "artifactHashes": {
    "manifest": "3e6b8975938693be08847b86286030cd7920cb89774d673126f44ac2c4e2ce2f",
    "packageLock": "36ccc2857b2e140e167bd0170be73b209e6d0377e6e23ed47b7ab2730e50e435",
    "releaseGate": "d76f3e78baac7f1ef944b68d22cc94dfbff77862f6f0a692a03ddfc064eff5ee",
    "nodeDeployment": "95fa1c466a39fcdf760427bb0a02ffd03cfbd5e0656dd6394e06ecbd09042d7a",
    "credentialsDeployment": "1a9eb26ea4a5bee0b7f5f04695b28c633fada78d03b7aa8909068a7e2f8ffae5"
  },
  "cleanup": {
    "secretsIncluded": false,
    "records": [
      {
        "stopped": 5,
        "remaining": [],
        "complete": true
      },
      {
        "stopped": 5,
        "remaining": [],
        "complete": true
      }
    ]
  }
}
